stealthtext/__init__.py
stealthtext/cli.py
stealthtext/encryption.py
StealthText-0.1.0.dist-info/METADATA
StealthText-0.1.0.dist-info/WHEEL
StealthText-0.1.0.dist-info/entry_points.txt
StealthText-0.1.0.dist-info/top_level.txt
StealthText-0.1.0.dist-info/RECORD
