Metadata-Version: 2.1
Name: StealthText
Version: 0.1.0
Summary: A simple encryption and decryption library for secure messaging.
Home-page: https://github.com/ByteBreach/StealthText
Author: MrFidal
Author-email: mrfidal@proton.me
Classifier: Programming Language :: Python :: 3
Classifier: License :: OSI Approved :: MIT License
Classifier: Operating System :: OS Independent
Requires-Python: >=3.6
Requires-Dist: cryptography
